{
    "boxShadow": "{{appsmith.theme.boxShadow.appBoxShadow}}",
    "borderColor": "#E0DEDE",
    "isVisibleDownload": true,
    "iconSVG": "/static/media/icon.c4395b694ca4b5a84741345b057b6866.svg",
    "topRow": 37,
    "isSortable": true,
    "type": "TABLE_WIDGET_V2",
    "inlineEditingSaveOption": "ROW_LEVEL",
    "animateLoading": true,
    "dynamicBindingPathList": [
        {"key": "accentColor"},
        {"key": "borderRadius"},
        {"key": "boxShadow"}
    ],
    "needsHeightForContent": true,
    "leftColumn": 1,
    "delimiter": ",",
    "defaultSelectedRowIndex": 0,
    "flexVerticalAlignment": "start",
    "accentColor": "{{appsmith.theme.colors.primaryColor}}",
    "isVisibleFilters": true,
    "isVisible": true,
    "enableClientSideSearch": true,
    "version": 2,
    "totalRecordsCount": 0,
    "tags": [
        "Suggested",
        "Display"
    ],
    "isLoading": false,
    "childStylesheet": {
        "button": {
            "boxShadow": "none",
            "borderRadius": "{{appsmith.theme.borderRadius.appBorderRadius}}",
            "buttonColor": "{{appsmith.theme.colors.primaryColor}}"
        },
        "iconButton": {
            "boxShadow": "none",
            "borderRadius": "{{appsmith.theme.borderRadius.appBorderRadius}}",
            "buttonColor": "{{appsmith.theme.colors.primaryColor}}"
        },
        "menuButton": {
            "boxShadow": "none",
            "borderRadius": "{{appsmith.theme.borderRadius.appBorderRadius}}",
            "menuColor": "{{appsmith.theme.colors.primaryColor}}"
        },
        "editActions": {
            "saveButtonColor": "{{appsmith.theme.colors.primaryColor}}",
            "saveBorderRadius": "{{appsmith.theme.borderRadius.appBorderRadius}}",
            "discardBorderRadius": "{{appsmith.theme.borderRadius.appBorderRadius}}",
            "discardButtonColor": "{{appsmith.theme.colors.primaryColor}}"
        }
    },
    "borderRadius": "{{appsmith.theme.borderRadius.appBorderRadius}}",
    "columnUpdatedAt": 1713816629633,
    "defaultSelectedRowIndices": [0],
    "needsErrorInfo": false,
    "mobileBottomRow": 61,
    "widgetName": "Table2",
    "defaultPageSize": 0,
    "columnOrder": [],
    "dynamicPropertyPathList": [],
    "displayName": "Table",
    "bottomRow": 65,
    "columnWidthMap": {},
    "parentRowSpace": 10,
    "hideCard": false,
    "mobileRightColumn": 35,
    "parentColumnSpace": 17.9375,
    "borderWidth": "1",
    "primaryColumns": {},
    "key": "n53dp4ux5x",
    "canFreezeColumn": true,
    "isDeprecated": false,
    "rightColumn": 46,
    "textSize": "0.875rem",
    "thumbnailSVG": "/static/media/thumbnail.d0492f06681daa69baf92b07d3829dfc.svg",
    "widgetId": "or6qytn9jc",
    "minWidth": 450,
    "tableData": "",
    "label": "Data",
    "searchKey": "",
    "parentId": "0",
    "renderMode": "CANVAS",
    "mobileTopRow": 33,
    "horizontalAlignment": "LEFT",
    "isVisibleSearch": true,
    "responsiveBehavior": "fill",
    "mobileLeftColumn": 1,
    "isVisiblePagination": true,
    "verticalAlignment": "CENTER"
}